{
  "_class": "shapePath",
  "booleanOperation": -1,
  "clippingMaskMode": 0,
  "do_objectID": "050F6AAE-E4DD-4F86-BFDF-8FAADD2B1691",
  "edited": true,
  "exportOptions": {
    "_class": "exportOptions",
    "exportFormats": [
    ],
    "includedLayerIds": [
    ],
    "layerOptions": 0,
    "shouldTrim": false
  },
  "frame": {
    "_class": "rect",
    "constrainProportions": false,
    "height": 5.300078706614721,
    "width": 5.300076355083321,
    "x": 1.130020954002259,
    "y": 1.119966779712286
  },
  "hasClippingMask": false,
  "isClosed": true,
  "isFixedToViewport": false,
  "isFlippedHorizontal": false,
  "isFlippedVertical": false,
  "isLocked": false,
  "isVisible": true,
  "layerListExpandedType": 0,
  "name": "Path",
  "nameIsFixed": false,
  "pointRadiusBehaviour": 1,
  "points": [
    {
      "_class": "curvePoint",
      "cornerRadius": 0,
      "curveFrom": "{0.29949581323394531, 1.0007601866979707}",
      "curveMode": 3,
      "curveTo": "{0.77729525164732505, 0.99895715792375261}",
      "hasCurveFrom": true,
      "hasCurveTo": true,
      "point": "{0.50189396847689349, 0.99999641498035707}"
    },
    {
      "_class": "curvePoint",
      "cornerRadius": 0,
      "curveFrom": "{-0.03936640933197167, 0.50588102686260339}",
      "curveMode": 2,
      "curveTo": "{0.11660203078310563, 0.87942634974007405}",
      "hasCurveFrom": true,
      "hasCurveTo": true,
      "point": "{0.03861781072556715, 0.692653688301339}"
    },
    {
      "_class": "curvePoint",
      "cornerRadius": 0,
      "curveFrom": "{0.28863853286327373, 0.0037398712177208471}",
      "curveMode": 2,
      "curveTo": "{0.0029438785039392857, 0.29051657506137601}",
      "hasCurveFrom": true,
      "hasCurveTo": true,
      "point": "{0.14579120568360651, 0.14712822313954826}"
    },
    {
      "_class": "curvePoint",
      "cornerRadius": 0,
      "curveFrom": "{0.87797406787834509, 0.11517066673986438}",
      "curveMode": 2,
      "curveTo": "{0.5038415783209782, -0.039384324881519002}",
      "hasCurveFrom": true,
      "hasCurveTo": true,
      "point": "{0.69090782309966148, 0.037893170929172861}"
    },
    {
      "_class": "curvePoint",
      "cornerRadius": 0,
      "curveFrom": "{1.0000019608702082, 0.77540696186556335}",
      "curveMode": 3,
      "curveTo": "{0.9999985589155268, 0.29760433350050025}",
      "hasCurveFrom": true,
      "hasCurveTo": true,
      "point": "{1, 0.50000384002242526}"
    }
  ],
  "resizingConstraint": 63,
  "resizingType": 0,
  "rotation": 0,
  "shouldBreakMaskChain": false,
  "style": {
    "_class": "style",
    "blur": {
      "_class": "blur",
      "center": "{0.5, 0.5}",
      "isEnabled": false,
      "motionAngle": 0,
      "radius": 10,
      "saturation": 1,
      "type": 0
    },
    "borderOptions": {
      "_class": "borderOptions",
      "dashPattern": [
      ],
      "isEnabled": true,
      "lineCapStyle": 0,
      "lineJoinStyle": 0
    },
    "borders": [
    ],
    "colorControls": {
      "_class": "colorControls",
      "brightness": 0,
      "contrast": 1,
      "hue": 0,
      "isEnabled": false,
      "saturation": 1
    },
    "contextSettings": {
      "_class": "graphicsContextSettings",
      "blendMode": 0,
      "opacity": 1
    },
    "do_objectID": "9EE00A98-4DFA-46A4-B7B0-A5C23D9DD1D2",
    "endMarkerType": 0,
    "fills": [
    ],
    "innerShadows": [
    ],
    "miterLimit": 10,
    "shadows": [
    ],
    "startMarkerType": 0,
    "windingRule": 1
  }
}